veilid/__init__.py
veilid/api.py
veilid/config.py
veilid/error.py
veilid/json_api.py
veilid/operations.py
veilid/schema/RecvMessage.json
veilid/schema/Request.json
veilid/state.py
veilid/types.py
veilid_python-0.1.0.dist-info/METADATA
veilid_python-0.1.0.dist-info/WHEEL
veilid_python-0.1.0.dist-info/RECORD
