Metadata-Version: 2.1
Name: veilid-python
Version: 0.1.0
Summary: 
Author: Christien Rioux
Author-email: chris@veilid.org
Requires-Python: >=3.11,<4.0
Classifier: Programming Language :: Python :: 3
Classifier: Programming Language :: Python :: 3.11
Classifier: Programming Language :: Python :: 3.12
Requires-Dist: jsonschema (>=4.17.3,<5.0.0)
